jipso/Client.py
jipso/Compute.py
jipso/Conversation.py
jipso/Input.py
jipso/Message.py
jipso/Output.py
jipso/Prompt.py
jipso/Room.py
jipso/Standard.py
jipso/Status.py
jipso/__init__.py
jipso/cli.py
jipso/init_db.py
jipso/pvp.py
jipso/update.py
jipso/utils.py
jipso/vendor/Anthropic.py
jipso/vendor/Gemini.py
jipso/vendor/Openai.py
jipso/vendor/Sberbank.py
jipso/vendor/Tencentcloud.py
jipso/vendor/Xai.py
jipso-0.1.37.dist-info/LICENSE
jipso-0.1.37.dist-info/METADATA
jipso-0.1.37.dist-info/WHEEL
jipso-0.1.37.dist-info/entry_points.txt
jipso-0.1.37.dist-info/RECORD
