Metadata-Version: 2.3
Name: jipso
Version: 0.1.37
Summary: JIPSO framework for prompt orchestration and comparison
License: Apache-2.0
Keywords: jipso,ai
Author: JIPSO Foundation
Author-email: contact@jipso.org
Requires-Python: >=3.10
Classifier: License :: OSI Approved :: Apache Software License
Classifier: Programming Language :: Python :: 3
Classifier: Programming Language :: Python :: 3.10
Classifier: Programming Language :: Python :: 3.11
Classifier: Programming Language :: Python :: 3.12
Classifier: Programming Language :: Python :: 3.13
Provides-Extra: all
Provides-Extra: byteplus
Provides-Extra: cloud
Provides-Extra: huggingface
Provides-Extra: local
Provides-Extra: ollama
Provides-Extra: tencent
Requires-Dist: anthropic (>=0.18.0)
Requires-Dist: byteplus-python-sdk-v2 (>=0.1.0) ; extra == "byteplus" or extra == "cloud" or extra == "all"
Requires-Dist: google-generativeai (>=0.1.0)
Requires-Dist: httpx (>=0.24.0)
Requires-Dist: ollama (>=0.1.0) ; extra == "ollama" or extra == "local" or extra == "all"
Requires-Dist: openai (>=1.0.0)
Requires-Dist: python-dotenv (>=1.0.0)
Requires-Dist: tencentcloud-sdk-python (>=0.1.0) ; extra == "tencent" or extra == "all"
Requires-Dist: torch (>=0.1.0) ; extra == "huggingface" or extra == "local" or extra == "all"
Requires-Dist: transformers (>=0.1.0) ; extra == "huggingface" or extra == "local" or extra == "all"
Requires-Dist: typer (>=0.12.0)
Requires-Dist: ujson (>=5.0.0)
Requires-Dist: xai-sdk (>=0.1.0)
Project-URL: Homepage, https://github.com/jipso-foundation/jipso-stack
Project-URL: Repository, https://github.com/jipso-foundation/jipso-stack
